planning_center_python/__init__.py
planning_center_python/api/__init__.py
planning_center_python/api/_pco_service.py
planning_center_python/api/_person_service.py
planning_center_python/api/abstract_http_client.py
planning_center_python/api/credentials.py
planning_center_python/api/http_client.py
planning_center_python/api/pco_client.py
planning_center_python/api/pco_token.py
planning_center_python/api/session.py
planning_center_python/data/api_response/pco_response.py
planning_center_python/errors.py
planning_center_python/models/__init__.py
planning_center_python/models/_pagination_params.py
planning_center_python/models/_url_date_filter.py
planning_center_python/models/_url_params_base.py
planning_center_python/models/pco_object.py
planning_center_python/models/person.py
planning_center_python/models/person_attributes.py
planning_center_python/models/webhook_signature.py
planning_center_python/settings.py
planning_center_python/util/_singleton_meta.py
planning_center_python-0.1.0.dist-info/LICENSE
planning_center_python-0.1.0.dist-info/METADATA
planning_center_python-0.1.0.dist-info/WHEEL
planning_center_python-0.1.0.dist-info/RECORD
