Metadata-Version: 2.3
Name: planning-center-python
Version: 0.1.0
Summary: Python wrappers for interacting with the Planning Center Online APIs
License: GNU GPLv3
Keywords: sdk,planning center online
Author: Andy Goellner
Author-email: andy.goellner@gmail.com
Maintainer: Andy Goellner
Maintainer-email: andy.goellner@gmail.com
Requires-Python: >=3.10,<3.13
Classifier: Development Status :: 2 - Pre-Alpha
Classifier: Programming Language :: Python :: 3.10
Classifier: Programming Language :: Python :: 3.11
Classifier: Programming Language :: Python :: 3.12
Classifier: Topic :: Software Development :: Libraries :: Python Modules
Classifier: Topic :: Internet
Requires-Dist: pydantic (>=2.8.0)
Requires-Dist: pydantic-settings (>=2.4.0)
Requires-Dist: requests (>=2.32.3)
Requires-Dist: requests-oauthlib (>=2.0.0)
Project-URL: Repository, https://github.com/andy-goellner/pco-python-sdk
